nifti_dynamic/__init__.py
nifti_dynamic/aorta_rois.py
nifti_dynamic/patlak.py
nifti_dynamic/tacs.py
nifti_dynamic/utils.py
nifti_dynamic/visualizations.py
nifti_dynamic/cli/__init__.py
nifti_dynamic/cli/extract_input_function.py
nifti_dynamic/cli/extract_tacs.py
nifti_dynamic/cli/resample_pet.py
nifti_dynamic/cli/voxel_patlak.py
nifti_dynamic-0.2.0.dist-info/METADATA
nifti_dynamic-0.2.0.dist-info/WHEEL
nifti_dynamic-0.2.0.dist-info/entry_points.txt
nifti_dynamic-0.2.0.dist-info/top_level.txt
nifti_dynamic-0.2.0.dist-info/RECORD
