Metadata-Version: 2.4
Name: nifti_dynamic
Version: 0.2.0
Summary: A package for dynamic NIFTI analysis
Classifier: Programming Language :: Python :: 3
Classifier: License :: OSI Approved :: MIT License
Classifier: Operating System :: OS Independent
Requires-Python: >=3.8
Requires-Dist: numpy
Requires-Dist: nibabel
Requires-Dist: indexed_gzip
Requires-Dist: scipy
Requires-Dist: scikit-learn
Requires-Dist: tqdm
Requires-Dist: ipython>=8.12.3
Requires-Dist: scikit-image>=0.21.0
Requires-Dist: matplotlib>=3.7.5
Requires-Dist: pandas>=2.0.3
Requires-Dist: opencv-python>=4.12.0.88
Requires-Dist: rich
Requires-Dist: typer
Requires-Dist: torch>=2.5.1
